agentcore/models.py
agentcore-0.1.6.dist-info/LICENSE
agentcore-0.1.6.dist-info/METADATA
agentcore-0.1.6.dist-info/WHEEL
agentcore-0.1.6.dist-info/RECORD
